NiukeShujukuSuoyinMianshiBikao15DianFix1/README.md
NiukeShujukuSuoyinMianshiBikao15DianFix1/__init__.py
NiukeShujukuSuoyinMianshiBikao15DianFix1/__main__.py
NiukeShujukuSuoyinMianshiBikao15DianFix1/file.epub
NiukeShujukuSuoyinMianshiBikao15DianFix1/index.html
NiukeShujukuSuoyinMianshiBikao15DianFix1/css/__init__.py
NiukeShujukuSuoyinMianshiBikao15DianFix1/css/annotations.css
NiukeShujukuSuoyinMianshiBikao15DianFix1/css/main.css
NiukeShujukuSuoyinMianshiBikao15DianFix1/css/normalize.css
NiukeShujukuSuoyinMianshiBikao15DianFix1/css/popup.css
NiukeShujukuSuoyinMianshiBikao15DianFix1/font/__init__.py
NiukeShujukuSuoyinMianshiBikao15DianFix1/font/fontello.eot
NiukeShujukuSuoyinMianshiBikao15DianFix1/font/fontello.svg
NiukeShujukuSuoyinMianshiBikao15DianFix1/font/fontello.ttf
NiukeShujukuSuoyinMianshiBikao15DianFix1/font/fontello.woff
NiukeShujukuSuoyinMianshiBikao15DianFix1/img/__init__.py
NiukeShujukuSuoyinMianshiBikao15DianFix1/img/annotator-glyph-sprite.png
NiukeShujukuSuoyinMianshiBikao15DianFix1/img/annotator-icon-sprite.png
NiukeShujukuSuoyinMianshiBikao15DianFix1/img/apple-touch-icon.png
NiukeShujukuSuoyinMianshiBikao15DianFix1/img/cancelfullscreen.png
NiukeShujukuSuoyinMianshiBikao15DianFix1/img/close.png
NiukeShujukuSuoyinMianshiBikao15DianFix1/img/fullscreen.png
NiukeShujukuSuoyinMianshiBikao15DianFix1/img/loader.gif
NiukeShujukuSuoyinMianshiBikao15DianFix1/img/menu-icon.png
NiukeShujukuSuoyinMianshiBikao15DianFix1/img/save.png
NiukeShujukuSuoyinMianshiBikao15DianFix1/img/saved.png
NiukeShujukuSuoyinMianshiBikao15DianFix1/img/settings-s.png
NiukeShujukuSuoyinMianshiBikao15DianFix1/img/settings.png
NiukeShujukuSuoyinMianshiBikao15DianFix1/img/star.png
NiukeShujukuSuoyinMianshiBikao15DianFix1/js/__init__.py
NiukeShujukuSuoyinMianshiBikao15DianFix1/js/epub.js
NiukeShujukuSuoyinMianshiBikao15DianFix1/js/epub.min.js
NiukeShujukuSuoyinMianshiBikao15DianFix1/js/epub.min.map
NiukeShujukuSuoyinMianshiBikao15DianFix1/js/hooks.min.js
niuke_shujuku_suoyin_mianshi_bikao_15_dian_fix1-2025.3.25.1.dist-info/METADATA
niuke_shujuku_suoyin_mianshi_bikao_15_dian_fix1-2025.3.25.1.dist-info/WHEEL
niuke_shujuku_suoyin_mianshi_bikao_15_dian_fix1-2025.3.25.1.dist-info/entry_points.txt
niuke_shujuku_suoyin_mianshi_bikao_15_dian_fix1-2025.3.25.1.dist-info/top_level.txt
niuke_shujuku_suoyin_mianshi_bikao_15_dian_fix1-2025.3.25.1.dist-info/RECORD
